milkstraw_client/__init__.py
milkstraw_client/_api_client.py
milkstraw_client/generated_data.py
milkstraw_client/model.py
milkstraw_client/source_data.py
milkstraw_client-1.0.2.dist-info/LICENSE
milkstraw_client-1.0.2.dist-info/METADATA
milkstraw_client-1.0.2.dist-info/WHEEL
milkstraw_client-1.0.2.dist-info/top_level.txt
milkstraw_client-1.0.2.dist-info/RECORD
