Metadata-Version: 2.1
Name: milkstraw-client
Version: 1.0.2
Summary: Generate synthetic data with a simple python client for milkstraw.ai
Author-email: "Milkstraw AI, Inc." <admin@milkstraw.ai>
License: Apache License
Project-URL: homepage, https://milkstraw.ai/
Project-URL: repository, https://github.com/milkstrawai/milkstraw-python-client
Keywords: milkstraw,generation,synthetic,augmentation,anonymization
Classifier: Programming Language :: Python :: 3.9
Classifier: License :: OSI Approved :: Apache Software License
Classifier: Intended Audience :: Developers
Classifier: Operating System :: OS Independent
Classifier: Topic :: Scientific/Engineering :: Artificial Intelligence
Requires-Python: >=3.9
License-File: LICENSE
Requires-Dist: requests ==2.31.0
